aecdata/__init__.py
aecdata/auth.py
aecdata/client.py
aecdata/productdata.py
aecdata/utils.py
aecdata-0.0.14.dist-info/licenses/LICENSE
tests/__init__.py
tests/test_client.py
aecdata-0.0.14.dist-info/METADATA
aecdata-0.0.14.dist-info/WHEEL
aecdata-0.0.14.dist-info/top_level.txt
aecdata-0.0.14.dist-info/RECORD
