Metadata-Version: 2.4
Name: aecdata
Version: 0.0.14
Summary: A Python library designed to simplify access to the 2050-materials API
Home-page: https://github.com/2050-Materials/aecdata
Author: 2050 Materials
Author-email: nicodemos@2050-materials.com
License: Apache License 2.0
Classifier: Programming Language :: Python :: 3
Classifier: License :: OSI Approved :: MIT License
Classifier: Operating System :: OS Independent
License-File: LICENSE
Requires-Dist: requests
Requires-Dist: numpy
Requires-Dist: pandas
Requires-Dist: pyarrow
Dynamic: author
Dynamic: author-email
Dynamic: classifier
Dynamic: description
Dynamic: description-content-type
Dynamic: home-page
Dynamic: license
Dynamic: license-file
Dynamic: requires-dist
Dynamic: summary
